{
  "badges": [
    {
      "firstName": "Richard",
      "lastName": "Kaufman",
      "email": "richardbkaufman@gmail.com",
      "avatarUrl": "https://www.gravatar.com/avatar/21594ed15d68ace3965642162f8d2e84?d=identicon",
      "jobTitle": "Frontend Engineer",
      "twitter": "sparragus",
      "id": "EYR2BVQ"
    },
    {
      "firstName": "Bruno",
      "lastName": "Cal",
      "email": "br1calolivera@gmail.com",
      "jobTitle": "Frontend Student",
      "twitter": "brunoo_cal",
      "id": "JhDuI5l"
    },
    {
      "firstName": "Facundo",
      "lastName": "Pérez",
      "email": "facuperez@gmail.com",
      "jobTitle": "Pro Player of Valorant",
      "twitter": "facuuu",
      "id": "SOLd_wn"
    },
    {
      "firstName": "Facundo",
      "lastName": "Cal",
      "email": "masterreviewservers@gmail.com",
      "jobTitle": "Frontend Engineer @ Google",
      "twitter": "brunoocal",
      "id": "wdCzpJ5"
    },
    {
      "firstName": "Bruno",
      "lastName": "Cal",
      "email": "br1calolivera@gmail.com",
      "jobTitle": "Frontend Engineer @ Google",
      "twitter": "brunoo_cal",
      "id": "vE3hdhb"
    }
  ]
}